blur_utils/__init__.py
blur_utils/_blur.py
blur_utils/_exceptions.py
blur_utils/_settings.py
blur_utils/_typing.py
blur_utils/_utils.py
blur_utils/py.typed
blur_utils-0.1.0.dist-info/LICENSE
blur_utils-0.1.0.dist-info/METADATA
blur_utils-0.1.0.dist-info/WHEEL
blur_utils-0.1.0.dist-info/RECORD
