Metadata-Version: 2.1
Name: blur-utils
Version: 0.1.0
Summary: Tiny package containing helpful classes and functions when blurring images
License: MIT
Author: galactixx
Requires-Python: >=3.10,<4.0
Classifier: License :: OSI Approved :: MIT License
Classifier: Programming Language :: Python :: 3
Classifier: Programming Language :: Python :: 3.10
Classifier: Programming Language :: Python :: 3.11
Classifier: Programming Language :: Python :: 3.12
Requires-Dist: numpy (>=2.1.1,<3.0.0)
Requires-Dist: opencv-python (>=4.10.0.84,<5.0.0.0)
Requires-Dist: pillow (>=10.4.0,<11.0.0)
Requires-Dist: pydantic (>=2.7.1,<3.0.0)
